README.md
setup.cfg
setup.py
changelogger/__init__.py
changelogger/cli.py
changelogger/elements.py
changelogger.egg-info/PKG-INFO
changelogger.egg-info/SOURCES.txt
changelogger.egg-info/dependency_links.txt
changelogger.egg-info/entry_points.txt
changelogger.egg-info/requires.txt
changelogger.egg-info/top_level.txt
changelogger.egg-info/zip-safe
changelogger/tests/__init__.py
changelogger/tests/mocks.py
changelogger/tests/test_elements.py