Metadata-Version: 1.2
Name: changelogger
Version: 0.1.0
Summary: Cli tool to auto-generate CHANGELOG from git commit.
Home-page: https://github.com/abawchen/changelogger
Author: Abaw Chen
Author-email: abaw.chen@gmail.com
License: MIT
Keywords: cli git changelog automation
Platform: UNKNOWN
Classifier: Development Status :: 3 - Alpha
Classifier: Intended Audience :: Developers
Classifier: Topic :: Software Development :: Libraries
Classifier: Programming Language :: Python :: 2.7
Classifier: Programming Language :: Python :: 3.3
Classifier: Programming Language :: Python :: 3.4
Classifier: Programming Language :: Python :: 3.5
Classifier: Programming Language :: Python :: 3.6
Classifier: Programming Language :: Python :: Implementation :: PyPy
Requires-Python: >=2.7
